AUTHORS.rst
CONTRIBUTING.rst
HISTORY.rst
LICENSE
MANIFEST.in
README.rst
setup.cfg
setup.py
dbix/__init__.py
dbix/builder.py
dbix/cli.py
dbix/dbix.py
dbix/mysql.py
dbix/perlconv.py
dbix/postgresql.py
dbix/schema.py
dbix/sqlite.py
dbix/sqlschema.py
dbix/trytonschema.py
dbix/tsql.py
dbix.egg-info/PKG-INFO
dbix.egg-info/SOURCES.txt
dbix.egg-info/dependency_links.txt
dbix.egg-info/entry_points.txt
dbix.egg-info/not-zip-safe
dbix.egg-info/requires.txt
dbix.egg-info/top_level.txt
docs/Makefile
docs/authors.rst
docs/conf.py
docs/contributing.rst
docs/history.rst
docs/index.rst
docs/installation.rst
docs/make.bat
docs/readme.rst
docs/usage.rst
tests/__init__.py
tests/config.json
tests/dumps
tests/test_dbix.py
tests/data/icecat.sqlite
tests/data/myapp.sqlite
tests/dumps/icecat.json
tests/dumps/icecat.sql
tests/dumps/myapp.json
tests/dumps/myapp.sql
tests/example/MyApp/Schema.pm
tests/example/MyApp/Schema/Result/Artist.pm
tests/example/MyApp/Schema/Result/Cd.pm
tests/example/MyApp/Schema/Result/Track.pm
tests/schema/Schema.pm
tests/schema/Schema/Result/Category.pm
tests/schema/Schema/Result/CategoryFeature.pm
tests/schema/Schema/Result/CategoryFeatureGroup.pm
tests/schema/Schema/Result/CategoryKeyword.pm
tests/schema/Schema/Result/Feature.pm
tests/schema/Schema/Result/FeatureGroup.pm
tests/schema/Schema/Result/FeatureLogo.pm
tests/schema/Schema/Result/FeatureLogoCategory.pm
tests/schema/Schema/Result/Language.pm
tests/schema/Schema/Result/Measure.pm
tests/schema/Schema/Result/MeasureSign.pm
tests/schema/Schema/Result/Product.pm
tests/schema/Schema/Result/ProductDescription.pm
tests/schema/Schema/Result/ProductFamily.pm
tests/schema/Schema/Result/ProductFeature.pm
tests/schema/Schema/Result/ProductFeatureLocal.pm
tests/schema/Schema/Result/ProductGallery.pm
tests/schema/Schema/Result/ProductMultimediaObject.pm
tests/schema/Schema/Result/ProductRelated.pm
tests/schema/Schema/Result/ProductReview.pm
tests/schema/Schema/Result/ProductSeries.pm
tests/schema/Schema/Result/SidIndex.pm
tests/schema/Schema/Result/Supplier.pm
tests/schema/Schema/Result/Tex.pm
tests/schema/Schema/Result/TidIndex.pm
tests/schema/Schema/Result/Vocabulary.pm