Metadata-Version: 1.1
Name: dbix
Version: 0.1.4
Summary: load a perl DBIx::Class schema with python
Home-page: https://github.com/alexbodn/python-dbix
Author: Alex Bodnaru
Author-email: alexbodn@gmail.com
License: Apache Software License 2.0
Keywords: dbix
Platform: UNKNOWN
Classifier: Development Status :: 4 - Beta
Classifier: Intended Audience :: Developers
Classifier: License :: OSI Approved :: Apache Software License
Classifier: Natural Language :: English
Classifier: Programming Language :: Python :: 2
Classifier: Programming Language :: Python :: 2.7
Classifier: Programming Language :: Python :: 3
Classifier: Programming Language :: Python :: 3.3
Classifier: Programming Language :: Python :: 3.4
Classifier: Programming Language :: Python :: 3.5
